{
  "call_id": "syn-billing-01",
  "domain": "billing",
  "seed": 2027,
  "turns": [
    {
      "speaker": "agent",
      "text": "Thanks for calling billing support, my name is Sam. How can I help today?",
      "pause_before": 0.0,
      "interrupt_prev": false,
      "event_tags": [
        {
          "event_type": "compliance",
          "subtype": "recording_disclosure",
          "polarity": "negative"
        }
      ]
    },
    {
      "speaker": "agent",
      "text": "To pull up your account, could you give me the billing email please?",
      "pause_before": 0.0,
      "interrupt_prev": false,
      "event_tags": [
        {
          "event_type": "compliance",
          "subtype": "identity_verification",
          "polarity": "positive"
        }
      ]
    },
    {
      "speaker": "customer",
      "text": "Sure, it's under my name and the usual email I sign in with.",
      "pause_before": 0.0,
      "interrupt_prev": false,
      "event_tags": []
    },
    {
      "speaker": "customer",
      "text": "I got charged twice this month and I only have one subscription.",
      "pause_before": 0.0,
      "interrupt_prev": false,
      "event_tags": []
    },
    {
      "speaker": "agent",
      "text": "I hear you. Let me see what's posted on the account this cycle.",
      "pause_before": 0.0,
      "interrupt_prev": false,
      "event_tags": []
    },
    {
      "speaker": "agent",
      "text": "So one of these looks like a duplicate. I can flag it for a refund.",
      "pause_before": 0.0,
      "interrupt_prev": false,
      "event_tags": []
    },
    {
      "speaker": "customer",
      "text": "So how long is it going to take to fix?",
      "pause_before": 0.0,
      "interrupt_prev": false,
      "event_tags": []
    },
    {
      "speaker": "customer",
      "text": "I just want to make sure this doesn't happen again next month.",
      "pause_before": 0.0,
      "interrupt_prev": true,
      "event_tags": [
        {
          "event_type": "interruption",
          "subtype": null,
          "polarity": null
        }
      ]
    },
    {
      "speaker": "customer",
      "text": "This is the third time I've called. Put me through to a manager.",
      "pause_before": 0.0,
      "interrupt_prev": false,
      "event_tags": [
        {
          "event_type": "escalation",
          "subtype": null,
          "polarity": null
        }
      ]
    },
    {
      "speaker": "agent",
      "text": "That's fair. I'll escalate this to a manager so we can sort it properly.",
      "pause_before": 0.0,
      "interrupt_prev": false,
      "event_tags": []
    },
    {
      "speaker": "agent",
      "text": "I've applied the refund and you'll see it in three to five days. Anything else?",
      "pause_before": 0.0,
      "interrupt_prev": false,
      "event_tags": []
    },
    {
      "speaker": "customer",
      "text": "That's all, appreciate it.",
      "pause_before": 0.0,
      "interrupt_prev": false,
      "event_tags": []
    }
  ],
  "notes": "recording_disclosure omitted; no silence"
}
